nexus_api/__init__.py
nexus_api/APINexus.py
nexus_api/email_alerts.py
nexus_api/exceptions.py
nexus_api/NexusRequest.py
nexus_api/NexusValue.py
nexus_integra_api-1.0.2.dist-info/LICENSE.MD
nexus_integra_api-1.0.2.dist-info/METADATA
nexus_integra_api-1.0.2.dist-info/WHEEL
nexus_integra_api-1.0.2.dist-info/RECORD
