Metadata-Version: 2.1
Name: nexus-integra-api
Version: 1.0.2
Summary:  Nexus API connection methods and utilities
Home-page: https://nexusintegra.io
Author: Nexus Integra
Requires-Python: >=3.7,<4.0
Classifier: Programming Language :: Python :: 3
Classifier: Programming Language :: Python :: 3.7
Classifier: Programming Language :: Python :: 3.8
Classifier: Programming Language :: Python :: 3.9
Classifier: Programming Language :: Python :: 3.10
Classifier: Programming Language :: Python :: 3.11
Requires-Dist: pandas
Requires-Dist: requests (>=2.28.1,<3.0.0)
Project-URL: Repository, https://github.com/NexusIntegra/NexusAPI
